model.py
langchain_alith-0.1.0.dist-info/METADATA
langchain_alith-0.1.0.dist-info/WHEEL
langchain_alith-0.1.0.dist-info/top_level.txt
langchain_alith-0.1.0.dist-info/RECORD
