Metadata-Version: 2.2
Name: langchain-alith
Version: 0.1.0
Summary: Langchain Alith Python Integration
License: Apache-2.0
Requires-Python: >=3.7
Requires-Dist: alith>=0.4.2
